mathmakerlib/LaTeX/__init__.py
mathmakerlib/LaTeX/attr_list.py
mathmakerlib/LaTeX/commands.py
mathmakerlib/LaTeX/environment.py
mathmakerlib/__init__.py
mathmakerlib/calculus/__init__.py
mathmakerlib/calculus/clocktime.py
mathmakerlib/calculus/equations/__init__.py
mathmakerlib/calculus/equations/equation.py
mathmakerlib/calculus/equations/pythagorean_equation.py
mathmakerlib/calculus/equations/templates/pythagorean_equation_autotest.tex
mathmakerlib/calculus/equations/templates/pythagorean_equation_calculate_hyp.tex
mathmakerlib/calculus/equations/templates/pythagorean_equation_calculate_hyp_detailed.tex
mathmakerlib/calculus/equations/templates/pythagorean_equation_calculate_leg0.tex
mathmakerlib/calculus/equations/templates/pythagorean_equation_calculate_leg0_detailed.tex
mathmakerlib/calculus/equations/templates/pythagorean_equation_calculate_leg0_shortcut.tex
mathmakerlib/calculus/equations/templates/pythagorean_equation_calculate_leg0_shortcut_detailed.tex
mathmakerlib/calculus/equations/templates/pythagorean_equation_calculate_leg1.tex
mathmakerlib/calculus/equations/templates/pythagorean_equation_calculate_leg1_detailed.tex
mathmakerlib/calculus/equations/templates/pythagorean_equation_calculate_leg1_shortcut.tex
mathmakerlib/calculus/equations/templates/pythagorean_equation_calculate_leg1_shortcut_detailed.tex
mathmakerlib/calculus/equations/templates/pythagorean_equation_calculate_square_hyp.tex
mathmakerlib/calculus/equations/templates/pythagorean_equation_calculate_square_legs_sum.tex
mathmakerlib/calculus/equations/templates/trigonometric_equation_calculate_adj_cos.tex
mathmakerlib/calculus/equations/templates/trigonometric_equation_calculate_adj_tan.tex
mathmakerlib/calculus/equations/templates/trigonometric_equation_calculate_adj_tan_div.tex
mathmakerlib/calculus/equations/templates/trigonometric_equation_calculate_angle_cos.tex
mathmakerlib/calculus/equations/templates/trigonometric_equation_calculate_angle_sin.tex
mathmakerlib-0.7.33.dist-info/LICENSE
mathmakerlib-0.7.33.dist-info/METADATA
mathmakerlib-0.7.33.dist-info/WHEEL
mathmakerlib-0.7.33.dist-info/RECORD
