Metadata-Version: 2.3
Name: mathmakerlib
Version: 0.7.33
Summary: Collection of lualatex-printable mathematical objects, including geometric shapes.
License: GPL-3.0-or-later
Author: Nicolas Hainaux
Author-email: nh.techn@posteo.net
Requires-Python: >=3.9,<3.13
Classifier: License :: OSI Approved :: GNU General Public License v3 or later (GPLv3+)
Classifier: Programming Language :: Python :: 3
Classifier: Programming Language :: Python :: 3.9
Classifier: Programming Language :: Python :: 3.10
Classifier: Programming Language :: Python :: 3.11
Classifier: Programming Language :: Python :: 3.12
Requires-Dist: sympy (>=1.13.3,<2.0.0)
